aigc_compliance/__init__.py
aigc_compliance/client.py
aigc_compliance/exceptions.py
aigc_compliance/models.py
aigc_compliance-1.0.2.dist-info/METADATA
aigc_compliance-1.0.2.dist-info/WHEEL
aigc_compliance-1.0.2.dist-info/licenses/LICENSE
aigc_compliance-1.0.2.dist-info/RECORD
