Metadata-Version: 2.4
Name: aigc-compliance
Version: 1.0.2
Summary: Official Python SDK for AIGC Compliance API - AI content detection and watermarking
Project-URL: Homepage, https://www.aigc-compliance.com
Project-URL: Documentation, https://www.aigc-compliance.com/docs
Project-URL: Repository, https://github.com/aigc-compliance/python-sdk
Project-URL: Changelog, https://github.com/aigc-compliance/python-sdk/blob/main/CHANGELOG.md
Project-URL: Bug Reports, https://github.com/aigc-compliance/python-sdk/issues
Author-email: AIGC Compliance Team <support@aigc-compliance.com>
License: MIT
License-File: LICENSE
Keywords: ai,compliance,content-safety,detection,watermark
Classifier: Development Status :: 5 - Production/Stable
Classifier: Intended Audience :: Developers
Classifier: License :: OSI Approved :: MIT License
Classifier: Programming Language :: Python :: 3
Classifier: Programming Language :: Python :: 3.7
Classifier: Programming Language :: Python :: 3.8
Classifier: Programming Language :: Python :: 3.9
Classifier: Programming Language :: Python :: 3.10
Classifier: Programming Language :: Python :: 3.11
Classifier: Programming Language :: Python :: 3.12
Classifier: Topic :: Internet :: WWW/HTTP :: Dynamic Content
Classifier: Topic :: Multimedia :: Graphics :: Graphics Conversion
Classifier: Topic :: Software Development :: Libraries :: Python Modules
Requires-Python: >=3.7
Requires-Dist: requests>=2.25.0
Requires-Dist: typing-extensions>=4.0.0; python_version < '3.8'
Provides-Extra: dev
Requires-Dist: black>=23.0.0; extra == 'dev'
Requires-Dist: build>=0.10.0; extra == 'dev'
Requires-Dist: flake8>=6.0.0; extra == 'dev'
Requires-Dist: mypy>=1.0.0; extra == 'dev'
Requires-Dist: pytest-cov>=4.0.0; extra == 'dev'
Requires-Dist: pytest>=7.0.0; extra == 'dev'
Requires-Dist: twine>=4.0.0; extra == 'dev'
